byml/__init__.py
byml/_version.py
byml/byml.py
byml/byml_to_yml.py
byml/yaml_util.py
byml/yml_to_byml.py
byml-2.4.5.post1.dist-info/LICENSE
byml-2.4.5.post1.dist-info/METADATA
byml-2.4.5.post1.dist-info/WHEEL
byml-2.4.5.post1.dist-info/entry_points.txt
byml-2.4.5.post1.dist-info/top_level.txt
byml-2.4.5.post1.dist-info/RECORD
