Metadata-Version: 2.1
Name: byml
Version: 2.4.5.post1
Summary: A simple Nintendo BYML or BYAML v2/v3 parser and writer
Home-page: https://github.com/leoetlino/byml-v2
Author: leoetlino
Author-email: leo@leolam.fr
Classifier: License :: OSI Approved :: GNU General Public License v2 or later (GPLv2+)
Classifier: Operating System :: OS Independent
Classifier: Programming Language :: Python :: 3 :: Only
Classifier: Topic :: Software Development :: Libraries
Requires-Python: >=3.6
License-File: LICENSE
Requires-Dist: PyYAML ~=6.0
Requires-Dist: sortedcontainers ~=2.0
Requires-Dist: oead ~=1.1
